LICENSE.txt
MANIFEST.in
README.md
SIDAnalyzer.py
setup.cfg
setup.py
SIDAnalyzer.egg-info/PKG-INFO
SIDAnalyzer.egg-info/SOURCES.txt
SIDAnalyzer.egg-info/dependency_links.txt
SIDAnalyzer.egg-info/top_level.txt