Metadata-Version: 2.1
Name: SIDAnalyzer
Version: 0.0.2
Summary: This script analyzes Microsoft SID.
Home-page: https://github.com/mauricelambert/SIDAnalyzer
Author: Maurice Lambert
Author-email: mauricelambert434@gmail.com
Maintainer: Maurice Lambert
Maintainer-email: mauricelambert434@gmail.com
License: GPL-3.0 License
Project-URL: Executable, https://mauricelambert.github.io/info/python/security/SIDAnalyzer.pyz
Keywords: SID,User,Forensic,Analysis,Microsoft,Identifier
Platform: Windows
Platform: Linux
Platform: MacOS
Classifier: Topic :: Security
Classifier: Environment :: Console
Classifier: Natural Language :: English
Classifier: Programming Language :: Python
Classifier: Programming Language :: Python :: 3.9
Classifier: Operating System :: MacOS
Classifier: Operating System :: POSIX :: Linux
Classifier: Operating System :: Microsoft :: Windows
Classifier: Development Status :: 5 - Production/Stable
Classifier: License :: OSI Approved :: GNU General Public License v3 (GPLv3)
Requires-Python: >=3.8
License-File: LICENSE.txt
